{"elapsed":"0.103","endpoint-url":"https://raw.githubusercontent.com/digital-land/ramsar-collection/main/data/ramsar-site.csv","entry-date":"2022-02-19T00:11:56.120371","request-headers":{"Accept":"*/*","Accept-Encoding":"gzip, deflate","Connection":"keep-alive","User-Agent":"DLUHC Digital Land"},"resource":"180e053855f7e5cb4963591ad82abb17077e002a0706a2d63ebe80eca3158535","response-headers":{"Accept-Ranges":"bytes","Access-Control-Allow-Origin":"*","Cache-Control":"max-age=300","Connection":"keep-alive","Content-Encoding":"gzip","Content-Length":"1863","Content-Security-Policy":"default-src 'none'; style-src 'unsafe-inline'; sandbox","Content-Type":"text/plain; charset=utf-8","Date":"Sat, 19 Feb 2022 00:11:58 GMT","ETag":"W/\"139d756aa26ddae611f64d50270713416ba05e118eda89e7bb4669e099f9eaf2\"","Expires":"Sat, 19 Feb 2022 00:16:58 GMT","Source-Age":"0","Strict-Transport-Security":"max-age=31536000","Vary":"Authorization,Accept-Encoding,Origin","Via":"1.1 varnish","X-Cache":"MISS","X-Cache-Hits":"0","X-Content-Type-Options":"nosniff","X-Fastly-Request-ID":"bcdf804593b4c828d7f7942093d027b95b24d28e","X-Frame-Options":"deny","X-GitHub-Request-Id":"BB42:3170:8214D9:9EA288:621035CE","X-Served-By":"cache-iad-kiad7000149-IAD","X-Timer":"S1645229518.356219,VS0,VE74","X-XSS-Protection":"1; mode=block"},"ssl-verify":true,"status":"200"}